CHANGES.txt
README.txt
TODO.txt
setup.py
bda/__init__.py
bda.contentproxy.egg-info/PKG-INFO
bda.contentproxy.egg-info/SOURCES.txt
bda.contentproxy.egg-info/dependency_links.txt
bda.contentproxy.egg-info/entry_points.txt
bda.contentproxy.egg-info/namespace_packages.txt
bda.contentproxy.egg-info/not-zip-safe
bda.contentproxy.egg-info/requires.txt
bda.contentproxy.egg-info/top_level.txt
bda/contentproxy/__init__.py
bda/contentproxy/configure.zcml
bda/contentproxy/duplexer.py
bda/contentproxy/interfaces.py
bda/contentproxy/profiles.zcml
bda/contentproxy/proxy.py
bda/contentproxy/version.txt
bda/contentproxy/browser/__init__.py
bda/contentproxy/browser/configure.zcml
bda/contentproxy/browser/content.pt
bda/contentproxy/browser/contentproxy.css
bda/contentproxy/browser/interfaces.py
bda/contentproxy/browser/proxy.pt
bda/contentproxy/browser/proxy.py
bda/contentproxy/browser/traversal.py
bda/contentproxy/browser/images/proxied_content_icon.png
bda/contentproxy/content/ATProxiedContent.py
bda/contentproxy/content/__init__.py
bda/contentproxy/content/interfaces.py
bda/contentproxy/profiles/default/cssregistry.xml
bda/contentproxy/profiles/default/factorytool.xml
bda/contentproxy/profiles/default/kssregistry.xml
bda/contentproxy/profiles/default/metadata.xml
bda/contentproxy/profiles/default/types.xml
bda/contentproxy/profiles/default/types/ATProxiedContent.xml
docs/bda.contentproxy.zuml