Metadata-Version: 1.0
Name: bda.contentproxy
Version: 1.0-beta5
Summary: module providing content proxying for plone.
Home-page: UNKNOWN
Author: Robert Niederreiter
Author-email: rnix@squarewave.at
License: General Public Licence
Platform: UNKNOWN
Classifier: Development Status :: 4 - Beta
Classifier: Environment :: Web Environment
Classifier: Framework :: Zope2
Classifier: License :: OSI Approved :: GNU General Public License (GPL)
Classifier: Operating System :: OS Independent
Classifier: Programming Language :: Python
Classifier: Topic :: Internet :: WWW/HTTP :: Dynamic Content
